{
  "experiment": "B4_LR_Decay",
  "seed": 42,
  "timestamp": "2026-03-22T20:01:27.832775",
  "records": [
    {
      "episode": 10,
      "train_loss": 0.7697435915470123,
      "train_acc": 0.7066666781902313,
      "val_acc": 0.7001333469152451,
      "avg_steps": 12.0
    },
    {
      "episode": 20,
      "train_loss": 0.7648269832134247,
      "train_acc": 0.7533333599567413,
      "val_acc": 0.754000015258789,
      "avg_steps": 6.5
    },
    {
      "episode": 30,
      "train_loss": 0.5782984495162964,
      "train_acc": 0.8400000184774399,
      "val_acc": 0.7945333528518677,
      "avg_steps": 6.25
    },
    {
      "episode": 40,
      "train_loss": 0.4716319069266319,
      "train_acc": 0.8833333551883698,
      "val_acc": 0.8346666845679284,
      "avg_steps": 6.25
    },
    {
      "episode": 50,
      "train_loss": 0.5440333336591721,
      "train_acc": 0.846666693687439,
      "val_acc": 0.8477333521842957,
      "avg_steps": 6.25
    },
    {
      "episode": 60,
      "train_loss": 0.46215834468603134,
      "train_acc": 0.8600000292062759,
      "val_acc": 0.8560000228881836,
      "avg_steps": 6.0
    },
    {
      "episode": 70,
      "train_loss": 0.288313876837492,
      "train_acc": 0.9566666930913925,
      "val_acc": 0.8757333523035049,
      "avg_steps": 5.75
    },
    {
      "episode": 80,
      "train_loss": 0.2705577313899994,
      "train_acc": 0.9366666823625565,
      "val_acc": 0.8942666888237,
      "avg_steps": 6.25
    },
    {
      "episode": 90,
      "train_loss": 0.2417989932000637,
      "train_acc": 0.9366666823625565,
      "val_acc": 0.8772000217437744,
      "avg_steps": 5.75
    },
    {
      "episode": 100,
      "train_loss": 0.3398737423121929,
      "train_acc": 0.9000000208616257,
      "val_acc": 0.9092000246047973,
      "avg_steps": 5.75
    },
    {
      "episode": 110,
      "train_loss": 0.24828200228512287,
      "train_acc": 0.9466666877269745,
      "val_acc": 0.8893333560228348,
      "avg_steps": 6.25
    },
    {
      "episode": 120,
      "train_loss": 0.24951725080609322,
      "train_acc": 0.9233333468437195,
      "val_acc": 0.8944000208377838,
      "avg_steps": 6.5
    },
    {
      "episode": 130,
      "train_loss": 0.31988197192549706,
      "train_acc": 0.906666710972786,
      "val_acc": 0.8986666923761368,
      "avg_steps": 6.0
    },
    {
      "episode": 140,
      "train_loss": 0.1951268296688795,
      "train_acc": 0.9733333587646484,
      "val_acc": 0.9150666874647141,
      "avg_steps": 6.0
    },
    {
      "episode": 150,
      "train_loss": 0.21959661692380905,
      "train_acc": 0.9500000178813934,
      "val_acc": 0.9240000212192535,
      "avg_steps": 6.0
    },
    {
      "episode": 160,
      "train_loss": 0.16453565657138824,
      "train_acc": 0.9600000232458115,
      "val_acc": 0.9004000240564346,
      "avg_steps": 6.0
    },
    {
      "episode": 170,
      "train_loss": 0.36784911435097456,
      "train_acc": 0.8833333402872086,
      "val_acc": 0.9021333557367325,
      "avg_steps": 6.0
    },
    {
      "episode": 180,
      "train_loss": 0.2525748535990715,
      "train_acc": 0.9366666972637177,
      "val_acc": 0.9084000211954116,
      "avg_steps": 6.0
    },
    {
      "episode": 190,
      "train_loss": 0.2355465665459633,
      "train_acc": 0.9333333522081375,
      "val_acc": 0.9162666875123978,
      "avg_steps": 6.0
    },
    {
      "episode": 200,
      "train_loss": 0.3790297545492649,
      "train_acc": 0.8266666978597641,
      "val_acc": 0.9080000221729279,
      "avg_steps": 6.0
    },
    {
      "episode": 210,
      "train_loss": 0.12830317672342062,
      "train_acc": 0.9666666835546494,
      "val_acc": 0.9142666888237,
      "avg_steps": 6.0
    },
    {
      "episode": 220,
      "train_loss": 0.13439922407269478,
      "train_acc": 0.9766666889190674,
      "val_acc": 0.9265333557128906,
      "avg_steps": 6.0
    },
    {
      "episode": 230,
      "train_loss": 0.2599588241428137,
      "train_acc": 0.9466666877269745,
      "val_acc": 0.9140000212192535,
      "avg_steps": 5.75
    },
    {
      "episode": 240,
      "train_loss": 0.18994231522083282,
      "train_acc": 0.9533333629369736,
      "val_acc": 0.9266666883230209,
      "avg_steps": 5.75
    },
    {
      "episode": 250,
      "train_loss": 0.3052323367446661,
      "train_acc": 0.9033333510160446,
      "val_acc": 0.9180000233650207,
      "avg_steps": 6.25
    },
    {
      "episode": 260,
      "train_loss": 0.15021722577512264,
      "train_acc": 0.9566666930913925,
      "val_acc": 0.9068000262975693,
      "avg_steps": 6.5
    },
    {
      "episode": 270,
      "train_loss": 0.21878013387322426,
      "train_acc": 0.9466667026281357,
      "val_acc": 0.9276000237464905,
      "avg_steps": 6.5
    },
    {
      "episode": 280,
      "train_loss": 0.18146312609314919,
      "train_acc": 0.9633333534002304,
      "val_acc": 0.928266687989235,
      "avg_steps": 6.75
    },
    {
      "episode": 290,
      "train_loss": 0.18133560754358768,
      "train_acc": 0.9600000083446503,
      "val_acc": 0.9230666917562484,
      "avg_steps": 6.25
    },
    {
      "episode": 300,
      "train_loss": 0.2019733153283596,
      "train_acc": 0.9533333629369736,
      "val_acc": 0.9262666893005371,
      "avg_steps": 6.25
    },
    {
      "episode": 310,
      "train_loss": 0.12534362636506557,
      "train_acc": 0.9766666740179062,
      "val_acc": 0.9190666890144348,
      "avg_steps": 6.0
    },
    {
      "episode": 320,
      "train_loss": 0.26146914064884186,
      "train_acc": 0.9133333563804626,
      "val_acc": 0.9262666898965836,
      "avg_steps": 5.5
    },
    {
      "episode": 330,
      "train_loss": 0.22821573913097382,
      "train_acc": 0.9366666972637177,
      "val_acc": 0.9282666873931885,
      "avg_steps": 5.75
    },
    {
      "episode": 340,
      "train_loss": 0.2158757969737053,
      "train_acc": 0.9366666823625565,
      "val_acc": 0.9273333537578583,
      "avg_steps": 6.0
    },
    {
      "episode": 350,
      "train_loss": 0.18997761234641075,
      "train_acc": 0.9466666877269745,
      "val_acc": 0.9429333531856536,
      "avg_steps": 6.25
    },
    {
      "episode": 360,
      "train_loss": 0.10779084824025631,
      "train_acc": 0.9933333396911621,
      "val_acc": 0.9253333562612533,
      "avg_steps": 5.75
    },
    {
      "episode": 370,
      "train_loss": 0.15054327249526978,
      "train_acc": 0.9733333587646484,
      "val_acc": 0.9326666885614395,
      "avg_steps": 5.75
    },
    {
      "episode": 380,
      "train_loss": 0.07542646955698729,
      "train_acc": 0.9833333492279053,
      "val_acc": 0.9285333544015885,
      "avg_steps": 5.75
    },
    {
      "episode": 390,
      "train_loss": 0.15668119117617607,
      "train_acc": 0.9500000178813934,
      "val_acc": 0.9429333573579788,
      "avg_steps": 6.75
    },
    {
      "episode": 400,
      "train_loss": 0.09378871554508805,
      "train_acc": 0.9766666740179062,
      "val_acc": 0.9380000227689743,
      "avg_steps": 5.75
    },
    {
      "episode": 410,
      "train_loss": 0.18356101773679256,
      "train_acc": 0.9600000232458115,
      "val_acc": 0.9445333516597748,
      "avg_steps": 6.0
    },
    {
      "episode": 420,
      "train_loss": 0.1262038517743349,
      "train_acc": 0.9566666930913925,
      "val_acc": 0.9404000216722488,
      "avg_steps": 5.75
    },
    {
      "episode": 430,
      "train_loss": 0.1633885893970728,
      "train_acc": 0.9600000083446503,
      "val_acc": 0.9421333557367325,
      "avg_steps": 5.25
    },
    {
      "episode": 440,
      "train_loss": 0.1599504016339779,
      "train_acc": 0.9433333426713943,
      "val_acc": 0.9417333537340165,
      "avg_steps": 6.0
    },
    {
      "episode": 450,
      "train_loss": 0.11662673018872738,
      "train_acc": 0.9833333492279053,
      "val_acc": 0.9341333556175232,
      "avg_steps": 5.75
    },
    {
      "episode": 460,
      "train_loss": 0.23538749665021896,
      "train_acc": 0.9300000220537186,
      "val_acc": 0.9420000213384628,
      "avg_steps": 5.75
    },
    {
      "episode": 470,
      "train_loss": 0.13395786471664906,
      "train_acc": 0.9733333587646484,
      "val_acc": 0.9345333558321,
      "avg_steps": 5.75
    },
    {
      "episode": 480,
      "train_loss": 0.1258839350193739,
      "train_acc": 0.9566666930913925,
      "val_acc": 0.9357333534955978,
      "avg_steps": 6.0
    },
    {
      "episode": 490,
      "train_loss": 0.11069733556360006,
      "train_acc": 0.9566666781902313,
      "val_acc": 0.9402666878700257,
      "avg_steps": 5.75
    },
    {
      "episode": 500,
      "train_loss": 0.08805061550810933,
      "train_acc": 0.9800000190734863,
      "val_acc": 0.9510666841268539,
      "avg_steps": 6.25
    },
    {
      "episode": 510,
      "train_loss": 0.09684906620532274,
      "train_acc": 0.9866666793823242,
      "val_acc": 0.9520000207424164,
      "avg_steps": 5.0
    },
    {
      "episode": 520,
      "train_loss": 0.14192623551934958,
      "train_acc": 0.9500000178813934,
      "val_acc": 0.9469333523511887,
      "avg_steps": 6.25
    },
    {
      "episode": 530,
      "train_loss": 0.0694681853055954,
      "train_acc": 0.9933333396911621,
      "val_acc": 0.9393333572149277,
      "avg_steps": 5.75
    },
    {
      "episode": 540,
      "train_loss": 0.09345404803752899,
      "train_acc": 0.9900000095367432,
      "val_acc": 0.9405333536863327,
      "avg_steps": 5.5
    },
    {
      "episode": 550,
      "train_loss": 0.13105015736073256,
      "train_acc": 0.9566666781902313,
      "val_acc": 0.946133354306221,
      "avg_steps": 5.75
    },
    {
      "episode": 560,
      "train_loss": 0.06565067358314991,
      "train_acc": 0.9900000095367432,
      "val_acc": 0.9289333534240722,
      "avg_steps": 6.0
    },
    {
      "episode": 570,
      "train_loss": 0.10450945235788822,
      "train_acc": 0.9699999988079071,
      "val_acc": 0.9384000217914581,
      "avg_steps": 5.25
    },
    {
      "episode": 580,
      "train_loss": 0.1004802817478776,
      "train_acc": 0.9766666889190674,
      "val_acc": 0.9534666854143142,
      "avg_steps": 5.75
    },
    {
      "episode": 590,
      "train_loss": 0.16669877525418997,
      "train_acc": 0.9266666918992996,
      "val_acc": 0.9513333529233933,
      "avg_steps": 6.0
    },
    {
      "episode": 600,
      "train_loss": 0.08094510808587074,
      "train_acc": 0.9866666793823242,
      "val_acc": 0.9465333527326584,
      "avg_steps": 5.25
    },
    {
      "episode": 610,
      "train_loss": 0.09464255161583424,
      "train_acc": 0.9800000190734863,
      "val_acc": 0.9341333538293839,
      "avg_steps": 5.75
    },
    {
      "episode": 620,
      "train_loss": 0.0453227034304291,
      "train_acc": 0.9900000095367432,
      "val_acc": 0.9448000222444535,
      "avg_steps": 6.5
    },
    {
      "episode": 630,
      "train_loss": 0.06067073065787554,
      "train_acc": 0.996666669845581,
      "val_acc": 0.9456000196933746,
      "avg_steps": 5.25
    },
    {
      "episode": 640,
      "train_loss": 0.09564023884013295,
      "train_acc": 0.9900000095367432,
      "val_acc": 0.9520000219345093,
      "avg_steps": 5.0
    },
    {
      "episode": 650,
      "train_loss": 0.07127472502179444,
      "train_acc": 0.9866666793823242,
      "val_acc": 0.9481333523988724,
      "avg_steps": 6.0
    },
    {
      "episode": 660,
      "train_loss": 0.12675131065770984,
      "train_acc": 0.9566666781902313,
      "val_acc": 0.9492000186443329,
      "avg_steps": 5.5
    },
    {
      "episode": 670,
      "train_loss": 0.16684937849640846,
      "train_acc": 0.9400000125169754,
      "val_acc": 0.9476000183820724,
      "avg_steps": 5.5
    },
    {
      "episode": 680,
      "train_loss": 0.15274189272895455,
      "train_acc": 0.9433333426713943,
      "val_acc": 0.9501333516836167,
      "avg_steps": 5.5
    },
    {
      "episode": 690,
      "train_loss": 0.1370071773417294,
      "train_acc": 0.9500000178813934,
      "val_acc": 0.9501333498954773,
      "avg_steps": 6.75
    },
    {
      "episode": 700,
      "train_loss": 0.12104117404669523,
      "train_acc": 0.9566666781902313,
      "val_acc": 0.9497333562374115,
      "avg_steps": 5.5
    },
    {
      "episode": 710,
      "train_loss": 0.11829024646431208,
      "train_acc": 0.9633333534002304,
      "val_acc": 0.9458666878938675,
      "avg_steps": 5.25
    },
    {
      "episode": 720,
      "train_loss": 0.08992489520460367,
      "train_acc": 0.9733333438634872,
      "val_acc": 0.9490666872262955,
      "avg_steps": 5.25
    },
    {
      "episode": 730,
      "train_loss": 0.16722372826188803,
      "train_acc": 0.9366666823625565,
      "val_acc": 0.9457333552837371,
      "avg_steps": 5.75
    },
    {
      "episode": 740,
      "train_loss": 0.06048624496906996,
      "train_acc": 0.9900000095367432,
      "val_acc": 0.9369333571195603,
      "avg_steps": 5.25
    },
    {
      "episode": 750,
      "train_loss": 0.05944506963714957,
      "train_acc": 0.9900000095367432,
      "val_acc": 0.9405333560705185,
      "avg_steps": 6.5
    },
    {
      "episode": 760,
      "train_loss": 0.14693626237567514,
      "train_acc": 0.9466666728258133,
      "val_acc": 0.9404000222682953,
      "avg_steps": 6.0
    },
    {
      "episode": 770,
      "train_loss": 0.08523853216320276,
      "train_acc": 0.9833333492279053,
      "val_acc": 0.9484000223875045,
      "avg_steps": 5.25
    },
    {
      "episode": 780,
      "train_loss": 0.10780987329781055,
      "train_acc": 0.9600000232458115,
      "val_acc": 0.9477333563566208,
      "avg_steps": 7.5
    },
    {
      "episode": 790,
      "train_loss": 0.04430219903588295,
      "train_acc": 0.9933333396911621,
      "val_acc": 0.9388000214099884,
      "avg_steps": 6.0
    },
    {
      "episode": 800,
      "train_loss": 0.05596424778923392,
      "train_acc": 0.9933333396911621,
      "val_acc": 0.9360000199079513,
      "avg_steps": 5.5
    },
    {
      "episode": 810,
      "train_loss": 0.08569657150655985,
      "train_acc": 0.9733333438634872,
      "val_acc": 0.947466686964035,
      "avg_steps": 7.0
    },
    {
      "episode": 820,
      "train_loss": 0.3050566278398037,
      "train_acc": 0.8733333498239517,
      "val_acc": 0.9585333549976349,
      "avg_steps": 5.5
    },
    {
      "episode": 830,
      "train_loss": 0.1265572813572362,
      "train_acc": 0.9700000137090683,
      "val_acc": 0.9560000199079514,
      "avg_steps": 6.0
    },
    {
      "episode": 840,
      "train_loss": 0.05742172524333,
      "train_acc": 0.9900000095367432,
      "val_acc": 0.941866688132286,
      "avg_steps": 6.0
    },
    {
      "episode": 850,
      "train_loss": 0.12112587038427591,
      "train_acc": 0.9666666835546494,
      "val_acc": 0.9457333546876907,
      "avg_steps": 6.0
    },
    {
      "episode": 860,
      "train_loss": 0.15803446155041456,
      "train_acc": 0.9433333426713943,
      "val_acc": 0.9456000232696533,
      "avg_steps": 5.75
    },
    {
      "episode": 870,
      "train_loss": 0.08984645828604698,
      "train_acc": 0.9766666889190674,
      "val_acc": 0.9537333548069,
      "avg_steps": 5.5
    },
    {
      "episode": 880,
      "train_loss": 0.11335375718772411,
      "train_acc": 0.9666666835546494,
      "val_acc": 0.946400021314621,
      "avg_steps": 6.0
    },
    {
      "episode": 890,
      "train_loss": 0.08350355736911297,
      "train_acc": 0.9800000190734863,
      "val_acc": 0.9548000204563141,
      "avg_steps": 5.5
    },
    {
      "episode": 900,
      "train_loss": 0.08163106138817966,
      "train_acc": 0.9866666793823242,
      "val_acc": 0.9513333541154861,
      "avg_steps": 6.25
    },
    {
      "episode": 910,
      "train_loss": 0.08140464825555682,
      "train_acc": 0.9800000190734863,
      "val_acc": 0.9552000206708908,
      "avg_steps": 6.0
    },
    {
      "episode": 920,
      "train_loss": 0.08378989435732365,
      "train_acc": 0.9833333492279053,
      "val_acc": 0.9545333528518677,
      "avg_steps": 6.25
    },
    {
      "episode": 930,
      "train_loss": 0.13095352426171303,
      "train_acc": 0.9500000178813934,
      "val_acc": 0.9512000226974487,
      "avg_steps": 5.75
    },
    {
      "episode": 940,
      "train_loss": 0.06159335980191827,
      "train_acc": 0.9833333492279053,
      "val_acc": 0.953066685795784,
      "avg_steps": 5.0
    },
    {
      "episode": 950,
      "train_loss": 0.13937138579785824,
      "train_acc": 0.9633333534002304,
      "val_acc": 0.9502666866779328,
      "avg_steps": 5.0
    },
    {
      "episode": 960,
      "train_loss": 0.05162437306717038,
      "train_acc": 0.9866666793823242,
      "val_acc": 0.9580000168085099,
      "avg_steps": 6.25
    },
    {
      "episode": 970,
      "train_loss": 0.11134926974773407,
      "train_acc": 0.9733333438634872,
      "val_acc": 0.9582666873931884,
      "avg_steps": 5.25
    },
    {
      "episode": 980,
      "train_loss": 0.196706498041749,
      "train_acc": 0.9300000220537186,
      "val_acc": 0.9540000188350678,
      "avg_steps": 5.5
    },
    {
      "episode": 990,
      "train_loss": 0.06672962056472898,
      "train_acc": 0.9866666793823242,
      "val_acc": 0.9648000192642212,
      "avg_steps": 6.25
    },
    {
      "episode": 1000,
      "train_loss": 0.08009479148313403,
      "train_acc": 0.9833333492279053,
      "val_acc": 0.9528000175952911,
      "avg_steps": 5.5
    },
    {
      "episode": 1010,
      "train_loss": 0.06315256468951702,
      "train_acc": 0.9900000095367432,
      "val_acc": 0.9468000197410583,
      "avg_steps": 5.25
    }
  ]
}